airbite/connectors.cpython-310-darwin.so
airbite/model_generator.cpython-310-darwin.so
airbite/__init__.cpython-310-darwin.so
airbite/hacks.cpython-310-darwin.so
airbite/util.cpython-310-darwin.so
airbite/connector_configs/__init__.cpython-310-darwin.so
airbite/connector_configs/model/source_file__0_5_15.cpython-310-darwin.so
airbite/connector_configs/model/destination_sftp_json__0_1_0.cpython-310-darwin.so
airbite/connector_configs/model/destination_csv__1_0_0.cpython-310-darwin.so
airbite/connector_configs/model/__init__.cpython-310-darwin.so
airbite/connector_configs/model/source_file__0_5_16.cpython-310-darwin.so
airbite-0.1.17.dist-info/RECORD
airbite-0.1.17.dist-info/WHEEL
airbite-0.1.17.dist-info/top_level.txt
airbite-0.1.17.dist-info/METADATA
