Metadata-Version: 2.1
Name: airbite
Version: 0.1.17
Summary: `airbite` brings the power of Airbyte to Python with an intuitive, user-friendly API. It builds upon the PyAirbyte project and adds additional features.
Home-page: https://github.com/ossmht/airbite_pub/
Author: ossmht
Author-email: ossmht@gmail.com
License: MIT
Keywords: airbite,airbyte,data,etl,extract,transform,load,pyairbyte
Classifier: Development Status :: 5 - Production/Stable
Classifier: License :: OSI Approved :: MIT License
Classifier: Operating System :: OS Independent
Classifier: Programming Language :: Python :: 3 :: Only
Requires-Dist: airbyte<0.999.0,>=0.21.0
Requires-Dist: pydantic>=2.10.2
Requires-Dist: airbyte_databricks_cache<0.999.0,>=0.1.7
